test_api.py
apifaker-0.0.1.dist-info/LICENSE
apifaker-0.0.1.dist-info/METADATA
apifaker-0.0.1.dist-info/WHEEL
apifaker-0.0.1.dist-info/top_level.txt
apifaker-0.0.1.dist-info/RECORD
